sodoku_detection/__init__.py
sodoku_detection/sodoku_detection.py
sodoku_detection-1.0.2.dist-info/METADATA
sodoku_detection-1.0.2.dist-info/WHEEL
sodoku_detection-1.0.2.dist-info/top_level.txt
sodoku_detection-1.0.2.dist-info/RECORD
