Metadata-Version: 2.1
Name: sodoku_detection
Version: 1.0.2
Summary: first package for test
Author: Sajedeh Gharabadiyan
Author-email: gharabadiyansajedeh@gmail.com
